{"name":"01 - Se realiza la compra exitosa de los suplementos deportivos","id":"el-usurio-realizar-la-compra-de-suplementos-deportivos;01---se-realiza-la-compra-exitosa-de-los-suplementos-deportivos","testSteps":[{"number":1,"description":"Given el usuario esta en la pagina de inicio del aplicativo zonafit","duration":6301,"startTime":"2022-12-30T19:01:21.466151-05:00[America/Bogota]","screenshots":[{"screenshot":"2f23b2dd43b3b58ede384b9a124b228a6ff1b15eea92e3d5e8ab5812daeaa505.png","timeStamp":1672444887767}],"result":"SUCCESS","precondition":false,"level":0,"children":[{"number":2,"description":"Messi open landing page","duration":3092,"startTime":"2022-12-30T19:01:24.669375700-05:00[America/Bogota]","screenshots":[{"screenshot":"ccee3ce00b5e9a9f649513c1047b4cc7239699ec6875f6a50eb195551fb49b33.png","timeStamp":1672444884835},{"screenshot":"2f23b2dd43b3b58ede384b9a124b228a6ff1b15eea92e3d5e8ab5812daeaa505.png","timeStamp":1672444887761}],"result":"SUCCESS","precondition":false,"level":1,"children":[{"number":3,"description":"Messi opens the Landing page","duration":2904,"startTime":"2022-12-30T19:01:24.850394500-05:00[America/Bogota]","screenshots":[{"screenshot":"ccee3ce00b5e9a9f649513c1047b4cc7239699ec6875f6a50eb195551fb49b33.png","timeStamp":1672444884856},{"screenshot":"2f23b2dd43b3b58ede384b9a124b228a6ff1b15eea92e3d5e8ab5812daeaa505.png","timeStamp":1672444887754}],"result":"SUCCESS","precondition":false,"level":2}]}]},{"number":4,"description":"When selecciono los productos para agregar al carrtio de compras","duration":20918,"startTime":"2022-12-30T19:01:27.775980300-05:00[America/Bogota]","screenshots":[{"screenshot":"dba7f2cbf04517564ea98d4ca60d3c3d9e5db1f92da895180d0974a497970354.png","timeStamp":1672444908694}],"result":"SUCCESS","precondition":false,"level":0,"children":[{"number":5,"description":"Messi pagina oferta","duration":1340,"startTime":"2022-12-30T19:01:27.786664600-05:00[America/Bogota]","screenshots":[{"screenshot":"1b8067df7a352476ff99986a0039b8d39e31414350493b871f1c2a221da40909.png","timeStamp":1672444889126}],"result":"SUCCESS","precondition":false,"level":1},{"number":6,"description":"Messi agregar carrito","duration":5173,"startTime":"2022-12-30T19:01:29.136089-05:00[America/Bogota]","screenshots":[{"screenshot":"1b8067df7a352476ff99986a0039b8d39e31414350493b871f1c2a221da40909.png","timeStamp":1672444889138},{"screenshot":"7969a2f3d84dc5b98881d4954f7b8b84daccc3d7aa736a02ce54b9405e16f094.png","timeStamp":1672444894309}],"result":"SUCCESS","precondition":false,"level":1,"children":[{"number":7,"description":"Messi clicks on Boton Ofertas","duration":818,"startTime":"2022-12-30T19:01:29.279099600-05:00[America/Bogota]","screenshots":[{"screenshot":"e6e3b104464b88d7061ede24ad8abffd09d198662857396c3bbd87c89ae286dc.png","timeStamp":1672444889534},{"screenshot":"db935a41a59b45e112a1effe32e1f0af1b2df01c3a8b67a93bc0e8fbb02d1965.png","timeStamp":1672444890097}],"result":"SUCCESS","precondition":false,"level":2},{"number":8,"description":"Messi clicks on btnClose","duration":4206,"startTime":"2022-12-30T19:01:30.100699500-05:00[America/Bogota]","screenshots":[{"screenshot":"db935a41a59b45e112a1effe32e1f0af1b2df01c3a8b67a93bc0e8fbb02d1965.png","timeStamp":1672444890104},{"screenshot":"7969a2f3d84dc5b98881d4954f7b8b84daccc3d7aa736a02ce54b9405e16f094.png","timeStamp":1672444894306}],"result":"SUCCESS","precondition":false,"level":2}]},{"number":9,"description":"Messi agregar carrito","duration":4016,"startTime":"2022-12-30T19:01:34.313968600-05:00[America/Bogota]","screenshots":[{"screenshot":"7969a2f3d84dc5b98881d4954f7b8b84daccc3d7aa736a02ce54b9405e16f094.png","timeStamp":1672444894317},{"screenshot":"ecf497d12ed73ce32fee8c2ed6d7c530b51ac7a610811dbddd081f9633c6b469.png","timeStamp":1672444898330}],"result":"SUCCESS","precondition":false,"level":1,"children":[{"number":10,"description":"Messi clicks on Boton Ofertas","duration":507,"startTime":"2022-12-30T19:01:34.459968700-05:00[America/Bogota]","screenshots":[{"screenshot":"14b2b062696da087f4ea49ab2837319c1c9f73d4afb14e65120050a14ea5d3cf.png","timeStamp":1672444894648},{"screenshot":"1facff8b42dcc0e35e6c1b9a384505f852c0c63cca21ef4d6832d62c897f81b6.png","timeStamp":1672444894966}],"result":"SUCCESS","precondition":false,"level":2},{"number":11,"description":"Messi clicks on btnClose","duration":3359,"startTime":"2022-12-30T19:01:34.967965-05:00[America/Bogota]","screenshots":[{"screenshot":"1facff8b42dcc0e35e6c1b9a384505f852c0c63cca21ef4d6832d62c897f81b6.png","timeStamp":1672444894971},{"screenshot":"ecf497d12ed73ce32fee8c2ed6d7c530b51ac7a610811dbddd081f9633c6b469.png","timeStamp":1672444898327}],"result":"SUCCESS","precondition":false,"level":2}]},{"number":12,"description":"Messi agregar carrito","duration":4179,"startTime":"2022-12-30T19:01:38.333241700-05:00[America/Bogota]","screenshots":[{"screenshot":"ecf497d12ed73ce32fee8c2ed6d7c530b51ac7a610811dbddd081f9633c6b469.png","timeStamp":1672444898336},{"screenshot":"0615d4f71b1f0b6af6e89850d3008a9c4f524a2d83d1391b7927781f7844badb.png","timeStamp":1672444902513}],"result":"SUCCESS","precondition":false,"level":1,"children":[{"number":13,"description":"Messi clicks on Boton Ofertas","duration":561,"startTime":"2022-12-30T19:01:38.590239-05:00[America/Bogota]","screenshots":[{"screenshot":"ef1aa2bdbfa9cdd98f7e374a847b1b50d402640b13019c0ad9472a2ab935c576.png","timeStamp":1672444898718},{"screenshot":"ff4e38f91915759487f6285cbeaf24f468b7ee105713c1ea15b259a4cd9d8d0e.png","timeStamp":1672444899151}],"result":"SUCCESS","precondition":false,"level":2},{"number":14,"description":"Messi clicks on btnClose","duration":3357,"startTime":"2022-12-30T19:01:39.153375200-05:00[America/Bogota]","screenshots":[{"screenshot":"ff4e38f91915759487f6285cbeaf24f468b7ee105713c1ea15b259a4cd9d8d0e.png","timeStamp":1672444899160},{"screenshot":"0615d4f71b1f0b6af6e89850d3008a9c4f524a2d83d1391b7927781f7844badb.png","timeStamp":1672444902511}],"result":"SUCCESS","precondition":false,"level":2}]}]},{"number":15,"description":"And da click en finalizar compra diligenciar el formulario correctamente","duration":13600,"startTime":"2022-12-30T19:01:48.696414400-05:00[America/Bogota]","screenshots":[{"screenshot":"1c67dfbbd0f594a7581c9f93dd0fdd410dbfef8af2d303b7e61eca8644111b72.png","timeStamp":1672444922297}],"result":"SUCCESS","precondition":false,"level":0,"children":[{"number":16,"description":"Messi finalizar compra","duration":7473,"startTime":"2022-12-30T19:01:48.704416800-05:00[America/Bogota]","screenshots":[{"screenshot":"60a565625e74a43c0940953a2992443276356dbd5a55fac55c8a0a41d707b857.png","timeStamp":1672444916177}],"result":"SUCCESS","precondition":false,"level":1,"children":[{"number":17,"description":"Messi clicks on Boton Ofertas","duration":359,"startTime":"2022-12-30T19:01:48.710411300-05:00[America/Bogota]","screenshots":[{"screenshot":"58d77b35ec3641121c978d8f03ae14f62c6563a2fcbce864f944c26d170af26e.png","timeStamp":1672444909070}],"result":"SUCCESS","precondition":false,"level":2},{"number":18,"description":"Messi clicks on btnClose","duration":3963,"startTime":"2022-12-30T19:01:52.209958600-05:00[America/Bogota]","screenshots":[{"screenshot":"b95c2af9c2144d812be3c58965893dd2c2017ae0974341830058673b6e7358a8.png","timeStamp":1672444912452},{"screenshot":"60a565625e74a43c0940953a2992443276356dbd5a55fac55c8a0a41d707b857.png","timeStamp":1672444916173}],"result":"SUCCESS","precondition":false,"level":2}]}]},{"number":19,"description":"Then aparece un mensaje Gracias. Tu pedido ha sido recibido.","duration":5196,"startTime":"2022-12-30T19:02:02.299062700-05:00[America/Bogota]","screenshots":[{"screenshot":"ea5a027de02e9518901db5db3d5c5674fe582495c9cd09de3fc8d9d411ec86c5.png","timeStamp":1672444927495}],"result":"SUCCESS","precondition":false,"level":0,"children":[{"number":20,"description":"Messi clears field Numero de documento","duration":439,"startTime":"2022-12-30T19:02:02.542045500-05:00[America/Bogota]","screenshots":[{"screenshot":"56cea3c0c2bff2d40018a2be2e1ceb32a5b03ce7419bd8fc74e6f96db2a2d9d1.png","timeStamp":1672444922653},{"screenshot":"2b24ebc6d59457d768bc8c1c097615102537247b095641938ef1c776d25948bc.png","timeStamp":1672444922980}],"result":"SUCCESS","precondition":false,"level":1},{"number":21,"description":"Messi enters \u0027771008\u0027 into Numero de documento","duration":262,"startTime":"2022-12-30T19:02:02.983690100-05:00[America/Bogota]","screenshots":[{"screenshot":"2b24ebc6d59457d768bc8c1c097615102537247b095641938ef1c776d25948bc.png","timeStamp":1672444922985},{"screenshot":"ab91c45183ae5a5aa824a36a6e77b16d9afc2d2c9d89d76960aac10a269719a5.png","timeStamp":1672444923246}],"result":"SUCCESS","precondition":false,"level":1},{"number":22,"description":"Messi clears field Email","duration":365,"startTime":"2022-12-30T19:02:03.297372800-05:00[America/Bogota]","screenshots":[{"screenshot":"f57d03a914c73ac0eee2b09f325c1c04b11c16033c8a880f9c7f6ff2ae2c34c8.png","timeStamp":1672444923417},{"screenshot":"658c39d4cf92b360463af0fd81ab4a78909da4e6aaf6a2b47795b6b2bd57cc50.png","timeStamp":1672444923662}],"result":"SUCCESS","precondition":false,"level":1},{"number":23,"description":"Messi enters \u0027CarlynSmith@gmail.com\u0027 into Email","duration":315,"startTime":"2022-12-30T19:02:03.663398300-05:00[America/Bogota]","screenshots":[{"screenshot":"658c39d4cf92b360463af0fd81ab4a78909da4e6aaf6a2b47795b6b2bd57cc50.png","timeStamp":1672444923666},{"screenshot":"00db2d85934205d56ec944dcec2e534c8877272ed2cf24157662428ac24b2573.png","timeStamp":1672444923978}],"result":"SUCCESS","precondition":false,"level":1},{"number":24,"description":"Messi clears field Nombre","duration":366,"startTime":"2022-12-30T19:02:04.036817800-05:00[America/Bogota]","screenshots":[{"screenshot":"566921a53003b77292a12f29a637159afdae6dd9383de3d5f6ba89e7732be8e6.png","timeStamp":1672444924146},{"screenshot":"1dbb873d827c88e97a483d064fd33464bc1d958a7a115ab3b8b990558b26bd6d.png","timeStamp":1672444924402}],"result":"SUCCESS","precondition":false,"level":1},{"number":25,"description":"Messi enters \u0027Carlyn\u0027 into Nombre","duration":297,"startTime":"2022-12-30T19:02:04.403878500-05:00[America/Bogota]","screenshots":[{"screenshot":"1dbb873d827c88e97a483d064fd33464bc1d958a7a115ab3b8b990558b26bd6d.png","timeStamp":1672444924405},{"screenshot":"e01aaaadc8f5fa8f5946ced141bbf87f5d849a7153daf64c939b1aa42572d98a.png","timeStamp":1672444924699}],"result":"SUCCESS","precondition":false,"level":1},{"number":26,"description":"Messi clears field Apellido","duration":348,"startTime":"2022-12-30T19:02:04.750869300-05:00[America/Bogota]","screenshots":[{"screenshot":"db9dc24ebb6fb6ca3d6b72ec2a40524f5a0f0e3485f5957a95bfdc4362d6f69b.png","timeStamp":1672444924861},{"screenshot":"f0db2ef31e112916698592534f42522cb33aaa51be2326b9c8c56db3c8eb0f3a.png","timeStamp":1672444925099}],"result":"SUCCESS","precondition":false,"level":1},{"number":27,"description":"Messi enters \u0027Smith\u0027 into Apellido","duration":301,"startTime":"2022-12-30T19:02:05.100799400-05:00[America/Bogota]","screenshots":[{"screenshot":"f0db2ef31e112916698592534f42522cb33aaa51be2326b9c8c56db3c8eb0f3a.png","timeStamp":1672444925103},{"screenshot":"90fb49e9b0b21eaff1b736d5076607ea12ce647f119e95980b0fbe5bf3b63ff2.png","timeStamp":1672444925402}],"result":"SUCCESS","precondition":false,"level":1},{"number":28,"description":"Messi clears field Direccion","duration":358,"startTime":"2022-12-30T19:02:05.453304200-05:00[America/Bogota]","screenshots":[{"screenshot":"445dc06265ffaf8adf8d27fcd741c240bbd40935603e2a9321321271405f644c.png","timeStamp":1672444925567},{"screenshot":"f18a2116331398b99904809ab698a3d2fcb38162300e612f53d7a1b34e7052ba.png","timeStamp":1672444925811}],"result":"SUCCESS","precondition":false,"level":1},{"number":29,"description":"Messi enters \u0027Suite 226 03128 Monnie Street, Lake Toddton, GA 86925\u0027 into Direccion","duration":335,"startTime":"2022-12-30T19:02:05.812724300-05:00[America/Bogota]","screenshots":[{"screenshot":"f18a2116331398b99904809ab698a3d2fcb38162300e612f53d7a1b34e7052ba.png","timeStamp":1672444925815},{"screenshot":"33f3aa768847261f5fc500b3e95225262c0a3bb18c4c1e63d1c907700ceba2a6.png","timeStamp":1672444926147}],"result":"SUCCESS","precondition":false,"level":1},{"number":30,"description":"Messi clears field Apartamento","duration":252,"startTime":"2022-12-30T19:02:06.149791-05:00[America/Bogota]","screenshots":[{"screenshot":"33f3aa768847261f5fc500b3e95225262c0a3bb18c4c1e63d1c907700ceba2a6.png","timeStamp":1672444926151},{"screenshot":"011099f1c7e7a21cf8e48cadecbfca7a55d34f51d74aaad46ec858ae530aac70.png","timeStamp":1672444926402}],"result":"SUCCESS","precondition":false,"level":1},{"number":31,"description":"Messi enters \u0027Suite 226 03128 Monnie Street, Lake Toddton, GA 86925\u0027 into Apartamento","duration":313,"startTime":"2022-12-30T19:02:06.403747-05:00[America/Bogota]","screenshots":[{"screenshot":"011099f1c7e7a21cf8e48cadecbfca7a55d34f51d74aaad46ec858ae530aac70.png","timeStamp":1672444926406},{"screenshot":"1a02abe4b9b80f40fdbcc6fd4697ea20f15ae271dd67f46d2b1c70254ea768d0.png","timeStamp":1672444926717}],"result":"SUCCESS","precondition":false,"level":1},{"number":32,"description":"Messi clears field Numero de celular","duration":357,"startTime":"2022-12-30T19:02:06.772084400-05:00[America/Bogota]","screenshots":[{"screenshot":"482140c6121c835930c91338dee5931e364c5120c4b26c6853a24008f2ffb725.png","timeStamp":1672444926878},{"screenshot":"00044164fc8ae9d31e99233394b55315a57b90e8303ce475e7f6fc0c9e708585.png","timeStamp":1672444927130}],"result":"SUCCESS","precondition":false,"level":1},{"number":33,"description":"Messi enters \u0027CarlynSmith@gmail.com\u0027 into Numero de celular","duration":358,"startTime":"2022-12-30T19:02:07.131981300-05:00[America/Bogota]","screenshots":[{"screenshot":"00044164fc8ae9d31e99233394b55315a57b90e8303ce475e7f6fc0c9e708585.png","timeStamp":1672444927133},{"screenshot":"ea5a027de02e9518901db5db3d5c5674fe582495c9cd09de3fc8d9d411ec86c5.png","timeStamp":1672444927490}],"result":"SUCCESS","precondition":false,"level":1}]}],"userStory":{"id":"el-usurio-realizar-la-compra-de-suplementos-deportivos","storyName":"El usurio realizar la compra de suplementos deportivos","path":"compraExitosa/compraExitosa.feature","narrative":"         en el aplicativo zonafit","type":"feature"},"featureTag":{"name":"Compra exitosa/El usurio realizar la compra de suplementos deportivos","type":"feature","displayName":"Compra exitosa/El usurio realizar la compra de suplementos deportivos"},"title":"01 - Se realiza la compra exitosa de los suplementos deportivos","description":"","tags":[{"name":"Compra exitosa/El usurio realizar la compra de suplementos deportivos","type":"feature","displayName":"El usurio realizar la compra de suplementos deportivos"},{"name":"Compra exitosa","type":"capability","displayName":"Compra exitosa"}],"startTime":"2022-12-30T19:01:21.336159200-05:00[America/Bogota]","duration":46161,"rule":{"name":"Como usuario quiero comprar suplementos deportivos","description":"        para el rendimiento deportivo"},"projectKey":"","sessionId":"9b501b5ba311c1a91d8d9d95db874126","driver":"chrome","isManualTestingUpToDate":false,"manual":false,"testSource":"Cucumber","actors":[{"name":"Messi","can":["browse the web"]}],"result":"SUCCESS"}